LICENSE
MANIFEST.in
README.md
setup.py
django_env/__init__.py
django_env/__init__.pyc
django_env/bin/__init__.py
django_env/bin/install.py
django_env/bin/postactivate
django_env/bin/postdeactivate
django_env/bin/postmkvirtualenv
django_env/bin/runserver
django_env/bin/uninstall.py
django_env/config/django_env_settings_template.txt
django_env/config/empty_fabfile.txt
django_env/utils/get_django_env_settings.py
django_env/utils/vcs.py
django_environment.egg-info/PKG-INFO
django_environment.egg-info/SOURCES.txt
django_environment.egg-info/dependency_links.txt
django_environment.egg-info/requires.txt
django_environment.egg-info/top_level.txt