Metadata-Version: 1.0
Name: django-environment
Version: 0.3.8
Summary: A plugin for virtualenvwrapper that makes setting up and creating new Django environments easier.
Home-page: http://github.com/epicserve/django-environment
Author: Brent O'Connor
Author-email: epicserve@gmail.com
License: UNKNOWN
Platform: UNKNOWN
Classifier: Development Status :: 4 - Beta
Classifier: Environment :: Web Environment
Classifier: Framework :: Django
Classifier: Intended Audience :: Developers
Classifier: Operating System :: OS Independent
Classifier: Programming Language :: Python
Classifier: Topic :: Software Development :: Libraries :: Python Modules
